pubpypack_harmony_ricardo_zambrano-0.0.5.dist-info/entry_points.txt
pubpypack_harmony_ricardo_zambrano-0.0.5.dist-info/RECORD
pubpypack_harmony_ricardo_zambrano-0.0.5.dist-info/METADATA
pubpypack_harmony_ricardo_zambrano-0.0.5.dist-info/WHEEL
pubpypack_harmony_ricardo_zambrano-0.0.5.dist-info/top_level.txt
pubpypack_harmony_ricardo_zambrano-0.0.5.dist-info/LICENSE
imppkg/py.typed
imppkg/hello.py
imppkg/data.json
imppkg/harmonic_mean.cpython-39-x86_64-linux-gnu.so
imppkg/harmonic_mean.c
imppkg/harmonic_mean.pyx
imppkg/__init__.py
imppkg/harmony.py
imppkg/__pycache__/hello.cpython-312.pyc
imppkg/__pycache__/__init__.cpython-312.pyc
