Metadata-Version: 2.1
Name: pubpypack-harmony-ricardo-zambrano
Version: 0.0.5
Summary: This package does amazing things
Home-page: https://github.com/rzambrano1/first-python-package
Author: Ricardo Zambrano
Author-email: "Ricardo Zambrano" <rzambrano@gmail.com>
License: MIT
Classifier: License :: OSI Approved :: MIT License
Requires-Python: >=3.9
License-File: LICENSE
Requires-Dist: termcolor<2,>=1.1.0
